tils/__init__.py
tils/uri.py
tils/zip.py
tils-0.0.2.dist-info/METADATA
tils-0.0.2.dist-info/WHEEL
tils-0.0.2.dist-info/licenses/LICENSE
tils-0.0.2.dist-info/RECORD
