Metadata-Version: 2.1
Name: tils
Version: 0.0.2
Summary: A Python package for storing reusable utilities.
Author-email: Michael Lucky <michael@llab.dev>
License-File: LICENSE
Classifier: License :: OSI Approved :: MIT License
Classifier: Operating System :: OS Independent
Classifier: Programming Language :: Python :: 3
Requires-Python: >=3.11
